vaex/astro/__init__.py
vaex/astro/_version.py
vaex/astro/astropy_table.py
vaex/astro/export.py
vaex/astro/fits.py
vaex/astro/gadget.py
vaex/astro/legacy.py
vaex/astro/tap.py
vaex/astro/transformations.py
vaex/astro/votable.py
vaex_astro-0.9.3.dist-info/LICENSE.txt
vaex_astro-0.9.3.dist-info/METADATA
vaex_astro-0.9.3.dist-info/WHEEL
vaex_astro-0.9.3.dist-info/entry_points.txt
vaex_astro-0.9.3.dist-info/top_level.txt
vaex_astro-0.9.3.dist-info/RECORD
