Metadata-Version: 1.0
Name: vaex-astro
Version: 0.9.3
Summary: Astronomy related transformations and FITS file support
Home-page: https://www.github.com/maartenbreddels/vaex
Author: Maarten A. Breddels
Author-email: maartenbreddels@gmail.com
License: MIT
Platform: UNKNOWN
